{
  "meta": {
    "timestamp": "2026-04-25 08:31",
    "cycle_type": "crypto",
    "machine": "primary",
    "dry_run": false
  },
  "summary": {
    "tickers_scanned": 18,
    "entries": 0,
    "exits": 0,
    "on_watch": 1,
    "portfolio_value": 101076.51,
    "cash": 75970.01,
    "buying_power": 177046.2
  },
  "trades": {
    "buys": [],
    "closes": []
  },
  "watch_list": [
    {
      "ticker": "XLM/USD",
      "score": 2,
      "price": 0.171892
    }
  ],
  "open_positions": {},
  "top_signals": [
    {
      "ticker": "XLM/USD",
      "score": 2,
      "action": "WATCH",
      "price": 0.171892
    },
    {
      "ticker": "NEAR/USD",
      "score": 1,
      "action": "HOLD",
      "price": 1.404
    },
    {
      "ticker": "BTC/USD",
      "score": 0,
      "action": "HOLD",
      "price": 77631.710938
    },
    {
      "ticker": "ETH/USD",
      "score": 0,
      "action": "HOLD",
      "price": 2316.790039
    },
    {
      "ticker": "SOL/USD",
      "score": 0,
      "action": "HOLD",
      "price": 86.57
    },
    {
      "ticker": "BNB/USD",
      "score": 0,
      "action": "HOLD",
      "price": 633.299988
    },
    {
      "ticker": "ADA/USD",
      "score": 0,
      "action": "HOLD",
      "price": 0.2524
    },
    {
      "ticker": "AVAX/USD",
      "score": 0,
      "action": "HOLD",
      "price": 9.41
    },
    {
      "ticker": "DOT/USD",
      "score": 0,
      "action": "HOLD",
      "price": 1.263
    },
    {
      "ticker": "LINK/USD",
      "score": 0,
      "action": "HOLD",
      "price": 9.414
    },
    {
      "ticker": "BCH/USD",
      "score": 0,
      "action": "HOLD",
      "price": 454.529999
    },
    {
      "ticker": "XRP/USD",
      "score": -1,
      "action": "HOLD",
      "price": 1.4312
    },
    {
      "ticker": "FIL/USD",
      "score": -1,
      "action": "HOLD",
      "price": 0.945
    },
    {
      "ticker": "DOGE/USD",
      "score": -2,
      "action": "HOLD",
      "price": 0.09824
    },
    {
      "ticker": "LTC/USD",
      "score": -2,
      "action": "HOLD",
      "price": 56.419998
    },
    {
      "ticker": "ALGO/USD",
      "score": -2,
      "action": "HOLD",
      "price": 0.1156
    },
    {
      "ticker": "ICP/USD",
      "score": -2,
      "action": "HOLD",
      "price": 2.455
    },
    {
      "ticker": "ATOM/USD",
      "score": -4,
      "action": "HOLD",
      "price": 2.039
    }
  ],
  "errors": []
}